{
  "date": "2026-01-19",
  "month": 1,
  "day": 19,
  "title": "Deléitate en el Señor",
  "verse": "Deléitate asimismo en Jehová, y él te concederá las peticiones de tu corazón.",
  "reference": "Salmos 37:4",
  "book": "Salmos",
  "reflection": "Este versículo no es un truco mágico para obtener lo que quieres. Es algo más profundo: cuando te deleitas genuinamente en Dios, tus deseos se transforman. Empiezas a querer lo que Él quiere, y entonces Él te concede esos deseos — porque ya están alineados con su voluntad.\n\nDeleitarse en Dios es encontrar tu mayor satisfacción en Él, no en las cosas que Él da. Es amarlo a Él, no solo sus beneficios. Cuando eso sucede, hay una libertad increíble.\n\nHoy, en lugar de pedirle cosas a Dios, simplemente disfruta de su presencia. Lee su Palabra sin agenda. Ora sin lista de peticiones. Deléitate en quién Él es, y descubrirás que tus deseos se purifican.",
  "tags": [
    "deleite",
    "deseos",
    "adoración"
  ]
}